{
  "$schema": "https://developer.microsoft.com/json-schemas/fabric/item/report/definition/visualContainer/2.4.0/schema.json",
  "name": "19bcaa90b69a3e0d8837",
  "position": {
    "x": 16,
    "y": 0,
    "z": 0,
    "height": 415.99999999999994,
    "width": 671.99999999999989,
    "tabOrder": 0
  },
  "visual": {
    "visualType": "clusteredColumnChart",
    "query": {
      "queryState": {
        "Category": {
          "projections": [
            {
              "field": {
                "HierarchyLevel": {
                  "Expression": {
                    "Hierarchy": {
                      "Expression": {
                        "SourceRef": {
                          "Entity": "Dim_date"
                        }
                      },
                      "Hierarchy": "Calendar"
                    }
                  },
                  "Level": "Année"
                }
              },
              "queryRef": "Dim_date.Calendrier.Année",
              "nativeQueryRef": "Calendrier Année",
              "active": true
            }
          ]
        },
        "Y": {
          "projections": [
            {
              "field": {
                "Measure": {
                  "Expression": {
                    "SourceRef": {
                      "Entity": "_Mesures"
                    }
                  },
                  "Property": "RevenueN-1"
                }
              },
              "queryRef": "_Mesures.RevenueN-1",
              "nativeQueryRef": "RevenueN-1"
            },
            {
              "field": {
                "Measure": {
                  "Expression": {
                    "SourceRef": {
                      "Entity": "_Mesures"
                    }
                  },
                  "Property": "Revenue"
                }
              },
              "queryRef": "_Mesures.Revenue",
              "nativeQueryRef": "Revenue"
            },
            {
              "field": {
                "Measure": {
                  "Expression": {
                    "SourceRef": {
                      "Entity": "_Mesures"
                    }
                  },
                  "Property": "RevenueWKND"
                }
              },
              "queryRef": "_Mesures.RevenueWKND",
              "nativeQueryRef": "RevenueWKND"
            }
          ]
        }
      },
      "sortDefinition": {
        "sort": [
          {
            "field": {
              "Measure": {
                "Expression": {
                  "SourceRef": {
                    "Entity": "_Mesures"
                  }
                },
                "Property": "RevenueN-1"
              }
            },
            "direction": "Descending"
          }
        ],
        "isDefaultSort": true
      }
    },
    "drillFilterOtherVisuals": true
  },
  "filterConfig": {
    "filters": [
      {
        "name": "de4789b3ebf00f75d72c",
        "field": {
          "HierarchyLevel": {
            "Expression": {
              "Hierarchy": {
                "Expression": {
                  "SourceRef": {
                    "Entity": "Dim_date"
                  }
                },
                "Hierarchy": "Calendar"
              }
            },
            "Level": "Année"
          }
        },
        "type": "Categorical",
        "filter": {
          "Version": 2,
          "From": [
            {
              "Name": "d",
              "Entity": "Dim_date",
              "Type": 0
            }
          ],
          "Where": [
            {
              "Condition": {
                "In": {
                  "Expressions": [
                    {
                      "Column": {
                        "Expression": {
                          "SourceRef": {
                            "Source": "d"
                          }
                        },
                        "Property": "Année"
                      }
                    }
                  ],
                  "Values": [
                    [
                      {
                        "Literal": {
                          "Value": "2017L"
                        }
                      }
                    ],
                    [
                      {
                        "Literal": {
                          "Value": "2018L"
                        }
                      }
                    ],
                    [
                      {
                        "Literal": {
                          "Value": "2016L"
                        }
                      }
                    ]
                  ]
                }
              },
              "Annotations": {
                "filterExpressionMetadata": {
                  "expressions": [
                    {
                      "HierarchyLevel": {
                        "Expression": {
                          "Hierarchy": {
                            "Expression": {
                              "SourceRef": {
                                "Entity": "Dim_date"
                              }
                            },
                            "Hierarchy": "Calendar"
                          }
                        },
                        "Level": "Année"
                      }
                    }
                  ],
                  "decomposedIdentities": {
                    "values": [
                      [
                        {
                          "0": [
                            {
                              "Literal": {
                                "Value": "2016L"
                              }
                            }
                          ]
                        }
                      ],
                      [
                        {
                          "0": [
                            {
                              "Literal": {
                                "Value": "2017L"
                              }
                            }
                          ]
                        }
                      ],
                      [
                        {
                          "0": [
                            {
                              "Literal": {
                                "Value": "2018L"
                              }
                            }
                          ]
                        }
                      ]
                    ],
                    "columns": [
                      {
                        "value": {
                          "Column": {
                            "Expression": {
                              "SourceRef": {
                                "Entity": "Dim_date"
                              }
                            },
                            "Property": "Année"
                          }
                        }
                      }
                    ]
                  },
                  "valueMap": [
                    {
                      "0": "2016"
                    },
                    {
                      "0": "2017"
                    },
                    {
                      "0": "2018"
                    }
                  ]
                }
              }
            }
          ]
        }
      }
    ]
  }
}